{
  "hot_list": [
    {
      "rank": 1,
      "word": "把思念写进一封家书",
      "hot_value": 12128829,
      "label": 3,
      "event_time": 1769772354
    },
    {
      "rank": 2,
      "word": "2026第一个月就要过完了",
      "hot_value": 11436866,
      "label": 3,
      "event_time": 1769819491
    },
    {
      "rank": 3,
      "word": "中国绿色低碳转型交出亮眼答卷",
      "hot_value": 11014752,
      "label": 3,
      "event_time": 1769758556
    },
    {
      "rank": 4,
      "word": "张帅组合获得澳网女双冠军",
      "hot_value": 10992466,
      "label": 1,
      "event_time": 1769828628
    },
    {
      "rank": 5,
      "word": "北方人对面食的执念有多深",
      "hot_value": 10181883,
      "label": 0,
      "event_time": 1769751720
    },
    {
      "rank": 6,
      "word": "烟火下心愿皆成",
      "hot_value": 10179880,
      "label": 1,
      "event_time": 1769829448
    },
    {
      "rank": 7,
      "word": "欧冠淘汰赛附加赛抽签出炉",
      "hot_value": 8802474,
      "label": 0,
      "event_time": 1769778616
    },
    {
      "rank": 8,
      "word": "外交部回应巴拿马涉港口有关裁决",
      "hot_value": 8341004,
      "label": 0,
      "event_time": 1769758921
    },
    {
      "rank": 9,
      "word": "美元创7月来最大单日涨幅",
      "hot_value": 7961943,
      "label": 1,
      "event_time": 1769824301
    },
    {
      "rank": 10,
      "word": "世贸争端案专家组驳回美方抗辩",
      "hot_value": 7826895,
      "label": 0,
      "event_time": 1769787788
    },
    {
      "rank": 11,
      "word": "生命树白菊妈妈反对女儿进山",
      "hot_value": 7816819,
      "label": 5,
      "event_time": 1769746734
    },
    {
      "rank": 12,
      "word": "蒹葭练胯舞蹈挑战",
      "hot_value": 7769151,
      "label": 9,
      "event_time": 1769774233
    },
    {
      "rank": 13,
      "word": "生命树剧情夯爆了",
      "hot_value": 7766593,
      "label": 0,
      "event_time": 1769773528
    },
    {
      "rank": 14,
      "word": "你是人间布洛芬太飙泪了",
      "hot_value": 7729048,
      "label": 3,
      "event_time": 1769768885
    },
    {
      "rank": 15,
      "word": "择天记3D动画开播",
      "hot_value": 7727250,
      "label": 5,
      "event_time": 1769829781
    },
    {
      "rank": 16,
      "word": "飞驰3张驰车队战力值满格了",
      "hot_value": 7725642,
      "label": 5,
      "event_time": 1769742950
    },
    {
      "rank": 17,
      "word": "此情此景什么文案最配呢",
      "hot_value": 7722597,
      "label": 0,
      "event_time": 1769824264
    },
    {
      "rank": 18,
      "word": "黄金白银大幅下跌",
      "hot_value": 7721319,
      "label": 0,
      "event_time": 1769817734
    },
    {
      "rank": 19,
      "word": "被安宥真弥渡山歌钓到了",
      "hot_value": 7708546,
      "label": 3,
      "event_time": 1769769034
    },
    {
      "rank": 20,
      "word": "孙千婚纱转场好戳泪",
      "hot_value": 7706107,
      "label": 3,
      "event_time": 1769761531
    }
  ],
  "update_time": "2026-01-31 05:01:51",
  "source": "抖音热榜",
  "category": "all",
  "is_test_data": false
}