{
  "hot_list": [
    {
      "rank": 1,
      "word": "日首相身体不适正接受治疗",
      "hot_value": 12100470,
      "label": 1,
      "event_time": 1769931450
    },
    {
      "rank": 2,
      "word": "2026年2月第一天",
      "hot_value": 11828783,
      "label": 3,
      "event_time": 1769903858
    },
    {
      "rank": 3,
      "word": "我国造船业三大指标领跑全球",
      "hot_value": 11451760,
      "label": 0,
      "event_time": 1769936516
    },
    {
      "rank": 4,
      "word": "也没人告诉我洛阳这么出片呀",
      "hot_value": 11358779,
      "label": 3,
      "event_time": 1769923767
    },
    {
      "rank": 5,
      "word": "绍伊古抵达北京",
      "hot_value": 10546720,
      "label": 1,
      "event_time": 1769934237
    },
    {
      "rank": 6,
      "word": "毛孩子也要过春节",
      "hot_value": 9421923,
      "label": 0,
      "event_time": 1769914855
    },
    {
      "rank": 7,
      "word": "东北糖葫芦让我充满惊喜",
      "hot_value": 9376327,
      "label": 0,
      "event_time": 1769915243
    },
    {
      "rank": 8,
      "word": "名侦探柯南声明",
      "hot_value": 9300328,
      "label": 3,
      "event_time": 1769914446
    },
    {
      "rank": 9,
      "word": "保罗·乔治禁赛25场",
      "hot_value": 9293832,
      "label": 3,
      "event_time": 1769903154
    },
    {
      "rank": 10,
      "word": "年夜饭提前演练起来",
      "hot_value": 9206712,
      "label": 0,
      "event_time": 1769825908
    },
    {
      "rank": 11,
      "word": "阿尔卡拉斯vs德约科维奇",
      "hot_value": 9123254,
      "label": 0,
      "event_time": 1769919690
    },
    {
      "rank": 12,
      "word": "粉碎涉铁路十大谣言",
      "hot_value": 9066606,
      "label": 16,
      "event_time": 1769829986
    },
    {
      "rank": 13,
      "word": "乌拉圭总统奥尔西抵达北京",
      "hot_value": 9025026,
      "label": 0,
      "event_time": 1769904279
    },
    {
      "rank": 14,
      "word": "什么是商业不动产REITs",
      "hot_value": 9004915,
      "label": 3,
      "event_time": 1769825746
    },
    {
      "rank": 15,
      "word": "河村勇辉公牛首秀",
      "hot_value": 8178768,
      "label": 3,
      "event_time": 1769914787
    },
    {
      "rank": 16,
      "word": "马德里不思议手势舞",
      "hot_value": 7822501,
      "label": 9,
      "event_time": 1769926260
    },
    {
      "rank": 17,
      "word": "曝金宣虎涉嫌逃税",
      "hot_value": 7811197,
      "label": 1,
      "event_time": 1769928351
    },
    {
      "rank": 18,
      "word": "谁还没吃水煮白开水",
      "hot_value": 7781351,
      "label": 9,
      "event_time": 1769860509
    },
    {
      "rank": 19,
      "word": "可爱Q版的我",
      "hot_value": 7766199,
      "label": 9,
      "event_time": 1769853733
    },
    {
      "rank": 20,
      "word": "大S离世近一年韩国节目制作特辑",
      "hot_value": 7763180,
      "label": 0,
      "event_time": 1769919118
    }
  ],
  "update_time": "2026-02-01 11:15:06",
  "source": "抖音热榜",
  "category": "all",
  "is_test_data": false
}