{
  "hot_list": [
    {
      "rank": 1,
      "word": "解放军军机飞进菲军演划设区",
      "hot_value": 12095580,
      "label": 3,
      "event_time": 1769828439
    },
    {
      "rank": 2,
      "word": "伊朗阿巴斯港楼房爆炸致1死14伤",
      "hot_value": 12084241,
      "label": 3,
      "event_time": 1769860588
    },
    {
      "rank": 3,
      "word": "2月起这些新规开始施行",
      "hot_value": 11885340,
      "label": 0,
      "event_time": 1769868049
    },
    {
      "rank": 4,
      "word": "这个冬天被抖音网友的善意暖到了",
      "hot_value": 11368924,
      "label": 0,
      "event_time": 1769865797
    },
    {
      "rank": 5,
      "word": "重返狼群导演亦风发声",
      "hot_value": 10742066,
      "label": 3,
      "event_time": 1769838793
    },
    {
      "rank": 6,
      "word": "把思念写进一封家书",
      "hot_value": 10454359,
      "label": 0,
      "event_time": 1769772354
    },
    {
      "rank": 7,
      "word": "辽宁男篮战胜天津",
      "hot_value": 9307294,
      "label": 0,
      "event_time": 1769855636
    },
    {
      "rank": 8,
      "word": "烟火下心愿皆成",
      "hot_value": 9299257,
      "label": 3,
      "event_time": 1769829448
    },
    {
      "rank": 9,
      "word": "T1 3:0 DK",
      "hot_value": 9124486,
      "label": 0,
      "event_time": 1769853741
    },
    {
      "rank": 10,
      "word": "伊媒否认革命卫队海军司令遭暗杀",
      "hot_value": 9116254,
      "label": 3,
      "event_time": 1769861092
    },
    {
      "rank": 11,
      "word": "AL 2:1 JDG",
      "hot_value": 9102276,
      "label": 0,
      "event_time": 1769855406
    },
    {
      "rank": 12,
      "word": "延边大学食堂阿姨受邀看春晚彩排",
      "hot_value": 9033812,
      "label": 3,
      "event_time": 1769821783
    },
    {
      "rank": 13,
      "word": "金价银价为何创纪录暴跌",
      "hot_value": 8813590,
      "label": 3,
      "event_time": 1769844625
    },
    {
      "rank": 14,
      "word": "俄罗斯重新将14名日本人列为战犯",
      "hot_value": 8741282,
      "label": 3,
      "event_time": 1769817236
    },
    {
      "rank": 15,
      "word": "突然的喜欢大结局",
      "hot_value": 8677847,
      "label": 0,
      "event_time": 1769863872
    },
    {
      "rank": 16,
      "word": "莱巴金娜首夺澳网桂冠",
      "hot_value": 8576483,
      "label": 0,
      "event_time": 1769855475
    },
    {
      "rank": 17,
      "word": "暗恋者的救赎大结局",
      "hot_value": 7837638,
      "label": 5,
      "event_time": 1769854881
    },
    {
      "rank": 18,
      "word": "应急管理部部长王祥喜被查",
      "hot_value": 7837544,
      "label": 0,
      "event_time": 1769846469
    },
    {
      "rank": 19,
      "word": "谁还没吃水煮白开水",
      "hot_value": 7836825,
      "label": 9,
      "event_time": 1769860509
    },
    {
      "rank": 20,
      "word": "生命树首播热度",
      "hot_value": 7828137,
      "label": 3,
      "event_time": 1769839549
    }
  ],
  "update_time": "2026-01-31 17:16:59",
  "source": "抖音热榜",
  "category": "all",
  "is_test_data": false
}