{
  "hot_list": [
    {
      "rank": 1,
      "word": "米兰冬奥会开幕式",
      "hot_value": 11962333,
      "label": "爆",
      "event_time": 1770362831
    },
    {
      "rank": 2,
      "word": "社火夜行祈福安康",
      "hot_value": 11646973,
      "label": "",
      "event_time": 1770446475
    },
    {
      "rank": 3,
      "word": "我国发射可重复使用试验航天器",
      "hot_value": 11308695,
      "label": "爆",
      "event_time": 1770440323
    },
    {
      "rank": 4,
      "word": "广州街头豫剧奶奶",
      "hot_value": 11204777,
      "label": "爆",
      "event_time": 1770424347
    },
    {
      "rank": 5,
      "word": "我有节目献给抖音非遗联欢会",
      "hot_value": 10392675,
      "label": "",
      "event_time": 1770368836
    },
    {
      "rank": 6,
      "word": "为了这口吃的专门旅了趟游",
      "hot_value": 10354677,
      "label": "爆",
      "event_time": 1770345156
    },
    {
      "rank": 7,
      "word": "新年仪式感从非遗旗袍开始",
      "hot_value": 9228119,
      "label": "爆",
      "event_time": 1770433300
    },
    {
      "rank": 8,
      "word": "苏翊鸣冲击中国队首金",
      "hot_value": 9108656,
      "label": "",
      "event_time": 1770447062
    },
    {
      "rank": 9,
      "word": "谷爱凌米兰冬奥首秀",
      "hot_value": 9044971,
      "label": "",
      "event_time": 1770425149
    },
    {
      "rank": 10,
      "word": "金晨肇事逃逸被罚1500元",
      "hot_value": 8908000,
      "label": "新",
      "event_time": 1770453772
    },
    {
      "rank": 11,
      "word": "EDG翻盘TYL晋级下一轮",
      "hot_value": 8728043,
      "label": "爆",
      "event_time": 1770406151
    },
    {
      "rank": 12,
      "word": "C罗因欠薪继续罢赛",
      "hot_value": 7823284,
      "label": "",
      "event_time": 1770428776
    },
    {
      "rank": 13,
      "word": "三角洲新春红人杯开打",
      "hot_value": 7817581,
      "label": "",
      "event_time": 1770445063
    },
    {
      "rank": 14,
      "word": "谷爱凌第一滑摔倒",
      "hot_value": 7793403,
      "label": "新",
      "event_time": 1770457081
    },
    {
      "rank": 15,
      "word": "王昶钱天一官宣领证",
      "hot_value": 7791043,
      "label": "",
      "event_time": 1770444281
    },
    {
      "rank": 16,
      "word": "我就当我的爱是罪是东流水",
      "hot_value": 7751926,
      "label": "音乐",
      "event_time": 1770422023
    },
    {
      "rank": 17,
      "word": "所有人现在跟我hello",
      "hot_value": 7751212,
      "label": "娱乐",
      "event_time": 1770437555
    },
    {
      "rank": 18,
      "word": "燕子娘的第一个镜头",
      "hot_value": 7750013,
      "label": "科技",
      "event_time": 1770436829
    },
    {
      "rank": 19,
      "word": "太平年郭荣抱憾离世",
      "hot_value": 7745654,
      "label": "荐",
      "event_time": 1770435498
    },
    {
      "rank": 20,
      "word": "海口警方通报3死1伤命案",
      "hot_value": 7743122,
      "label": "爆",
      "event_time": 1770419646
    }
  ],
  "update_time": "2026-02-07 10:17:11",
  "source": "抖音热榜",
  "category": "all",
  "is_test_data": false
}